<?xml version="1.0" encoding="UTF-8"?>
<objects serializationModel="Studio.02.02.00">
	<object class="EncodingSetting" id="{1822a613-6d54-495e-82c9-0481cdb07b0b}">
		<property name="encodingFormat">
			<value>3</value>
		</property>
		<property name="quality">
			<value>37</value>
		</property>
		<relationship name="platform">
			<destination>{12dfe7f1-2cff-443e-b195-ca7421655c1e}</destination>
		</relationship>
		<relationship name="encodable">
			<destination>{6a98db8a-d930-4f39-ad38-4929f102ee85}</destination>
		</relationship>
	</object>
</objects>
